django_error_reporting/__init__.py
django_error_reporting/apps.py
django_error_reporting/constants.py
django_error_reporting/middleware.py
django_error_reporting/settings.py
django_error_reporting/utils.py
django_error_reporting/contrib/__init__.py
django_error_reporting/contrib/datadog.py
django_error_reporting/contrib/sentry.py
django_error_reporting/migrations/__init__.py
test_app/__init__.py
test_app/settings.py
test_app/urls.py
test_app/views.py
test_app/wsgi.py
django_error_reporting-0.10.1.dist-info/METADATA
django_error_reporting-0.10.1.dist-info/WHEEL
django_error_reporting-0.10.1.dist-info/top_level.txt
django_error_reporting-0.10.1.dist-info/RECORD
