Metadata-Version: 2.4
Name: django-error-reporting
Version: 0.10.1
Summary: DataDog and Sentry error reporting for Django
Home-page: https://github.com/Lenders-Cooperative/django-error-reporting
Author: Logan Bibby <lbibby@thesummitgrp.com>
Classifier: Programming Language :: Python :: 3
Classifier: License :: OSI Approved :: BSD License
Classifier: Operating System :: OS Independent
Requires-Python: >=3.6
Requires-Dist: django>=2.2.9
Requires-Dist: sentry-sdk>=1.5.4
Requires-Dist: ddtrace>=0.59.0
Requires-Dist: django-datadog-logger>=0.5.0
